[{"id":"1","name":"Antanas","lastname":"Jonaitis","AC":"LT721612009127467484","PC":"39305311112","balance":81},{"id":"2","name":"Petras","lastname":"Antaninis","AC":"LT357847611156580578","PC":"39705322222","balance":0},{"id":"3","name":"Kazimieras","lastname":"Vaidutis","AC":"LT304606148798308474","PC":"39005333333","balance":432.5},{"id":"4","name":"Vakaris","lastname":"Rytas","AC":"LT537646792991849533","PC":"38205344444","balance":0},{"id":"5","name":"Lina","lastname":"Jonait\u0117","AC":"LT203343047743715862","PC":"48705555555","balance":15},{"id":"6","name":"Ona","lastname":"Jonaitiene","AC":"LT994825263236151068","PC":"48705555555","balance":1000}]